uniquebible/htmlResources/images/exlbl_largeHD_3/BL1000.png
uniquebible/htmlResources/images/exlbl_largeHD_3/BL1001.png
uniquebible/htmlResources/images/exlbl_largeHD_3/BL1002.png
uniquebible/htmlResources/images/exlbl_largeHD_3/BL1003.png
uniquebible/htmlResources/images/exlbl_largeHD_3/BL1004.png
uniquebible/htmlResources/images/exlbl_largeHD_3/BL1006.png
uniquebible/htmlResources/images/exlbl_largeHD_3/BL1007.png
uniquebible/htmlResources/images/exlbl_largeHD_3/BL1008.png
uniquebible/htmlResources/images/exlbl_largeHD_3/BL1009.png
uniquebible/htmlResources/images/exlbl_largeHD_3/BL1012.png
uniquebible/htmlResources/images/exlbl_largeHD_3/BL1013.png
uniquebible/htmlResources/images/exlbl_largeHD_3/BL1014.png
uniquebible/htmlResources/images/exlbl_largeHD_3/BL1016.png
uniquebible/htmlResources/images/exlbl_largeHD_3/BL1017.png
uniquebible/htmlResources/images/exlbl_largeHD_3/BL1018.png
uniquebible/htmlResources/images/exlbl_largeHD_3/BL1019.png
uniquebible/htmlResources/images/exlbl_largeHD_3/BL1020.png
uniquebible/htmlResources/images/exlbl_largeHD_3/BL1021.png
uniquebible/htmlResources/images/exlbl_largeHD_3/BL1022.png
uniquebible/htmlResources/images/exlbl_largeHD_3/BL1023.png
uniquebible/htmlResources/images/exlbl_largeHD_3/BL1024.png
uniquebible/htmlResources/images/exlbl_largeHD_3/BL1025.png
uniquebible/htmlResources/images/exlbl_largeHD_3/BL1026.png
uniquebible/htmlResources/images/exlbl_largeHD_3/BL1027.png
uniquebible/htmlResources/images/exlbl_largeHD_3/BL1028.png
uniquebible/htmlResources/images/exlbl_largeHD_3/BL1029.png
uniquebible/htmlResources/images/exlbl_largeHD_3/BL1030.png
uniquebible/htmlResources/images/exlbl_largeHD_3/BL1032.png
uniquebible/htmlResources/images/exlbl_largeHD_3/BL1034.png
uniquebible/htmlResources/images/exlbl_largeHD_3/BL1037.png
uniquebible/htmlResources/images/exlbl_largeHD_3/BL1038.png
uniquebible/htmlResources/images/exlbl_largeHD_3/BL1039.png
uniquebible/htmlResources/images/exlbl_largeHD_3/BL1040.png
uniquebible_maps_5-0.0.3.dist-info/LICENSE
uniquebible_maps_5-0.0.3.dist-info/METADATA
uniquebible_maps_5-0.0.3.dist-info/WHEEL
uniquebible_maps_5-0.0.3.dist-info/top_level.txt
uniquebible_maps_5-0.0.3.dist-info/RECORD
